ezmsg/neo/__init__.py
ezmsg/neo/__version__.py
ezmsg/neo/source.py
ezmsg_neo-0.4.0.dist-info/METADATA
ezmsg_neo-0.4.0.dist-info/WHEEL
ezmsg_neo-0.4.0.dist-info/licenses/LICENSE
ezmsg_neo-0.4.0.dist-info/RECORD
