Metadata-Version: 2.4
Name: ezmsg-neo
Version: 0.4.0
Summary: Load and stream data from neo files into ezmsg.
Author-email: Chadwick Boulay <chadwick.boulay@gmail.com>
License-Expression: MIT
License-File: LICENSE
Requires-Python: >=3.10.15
Requires-Dist: ezmsg>=3.6.0
Requires-Dist: neo>=0.13.4
Requires-Dist: numba>=0.61.0
Requires-Dist: numpy>=2.2.6
Requires-Dist: sparse>=0.17.0
